flexinet/__init__.py
flexinet/_io/__init__.py
flexinet/_io/_load_torch.py
flexinet/_io/_read_h5ad.py
flexinet/_models/_LinearVAE.py
flexinet/_models/__init__.py
flexinet/_models/_autoencoder.py
flexinet/_models/_compose_nn_sequential.py
flexinet/_models/_potential_net.py
flexinet/_models/_supporting_functions/_KL_Divergence.py
flexinet/_models/_supporting_functions/_Learner.py
flexinet/_models/_supporting_functions/_OptimalTransportLoss.py
flexinet/_models/_supporting_functions/_build_encoder_decoder.py
flexinet/_models/_supporting_functions/_compose_multilayered_nn_sequential.py
flexinet/_models/_supporting_functions/_plot_loss.py
flexinet/_models/_supporting_functions/_reparameterize.py
flexinet/_models/_supporting_functions/_training_loop.py
flexinet/_models/_supporting_functions/_utilities.py
flexinet/_preprocessing/__init__.py
flexinet/_preprocessing/_split_train_validation_test_at_random.py
flexinet/_utilities/_get_device.py
flexinet-0.0.4.dist-info/LICENSE
flexinet-0.0.4.dist-info/METADATA
flexinet-0.0.4.dist-info/WHEEL
flexinet-0.0.4.dist-info/top_level.txt
flexinet-0.0.4.dist-info/RECORD
