Metadata-Version: 2.1
Name: flexinet
Version: 0.0.4
Summary: Flexible torch neural network architecture API
Home-page: https://github.com/mvinyard/flexinet
Author: Michael E. Vinyard - Harvard University - Massachussetts General Hospital - Broad Institute of MIT and Harvard
Author-email: mvinyard@broadinstitute.org
License: MIT
Platform: UNKNOWN
Classifier: Development Status :: 2 - Pre-Alpha
Classifier: Programming Language :: Python :: 3.6
Classifier: Intended Audience :: Science/Research
Classifier: Topic :: Scientific/Engineering :: Bio-Informatics
Requires-Python: >3.6.0
License-File: LICENSE
Requires-Dist: anndata (>=0.7.8)
Requires-Dist: numpy (>=1.17.0)
Requires-Dist: torch (>=1.10.1)
Requires-Dist: licorice-font (>=0.0.3)
Requires-Dist: geomloss (>=0.2.3)
